full_adder/hdl/half_adder.v
`timescale 1ns/1ns

module half_adder 
	(
		input a,
		input b,

		output sum,
		output carry
	);

	assign sum   = a ^ b;  // bitwise xor
	assign carry = a & b;  // bitwise and
endmodule // half_adder

threebit_adder/hdl/full_adder.v
`timescale 1ns/1ns

module full_adder
	(
		input a,
		input b,
		input carry_in,
		
		output sum,
		output carry_out
	);
	
	// internal signals
	wire stage1_sum;
	wire stage1_carry;
	wire stage2_carry;
	
	half_adder stage1
	(
		.a(a),
		.b(b),
		.sum(stage1_sum),
		.carry(stage1_carry)
	);
	
	half_adder stage2
	(
		.a(stage1_sum),
		.b(carry_in), 
		.sum(sum),
		.carry(stage2_carry)
	);
	
	or(carry_out, stage1_carry, stage2_carry);
	
endmodule

full_adder/testbench/full_adder_tb.v
`timescale 1ns/1ns

module full_adder_tb;
	// Inputs
	reg t_a;
	reg t_b;
	reg t_carry_in;

	// Outputs
	wire t_sum;
	wire t_carry_out;

	// Instantiate the Unit Under Test (UUT)
	full_adder UUT (
		.a(t_a), 
		.b(t_b),
		.carry_in(t_carry_in),
		.sum(t_sum), 
		.carry_out(t_carry_out)
	);

	initial begin
		$dumpfile("haout.vcd");
		$dumpvars(1, full_adder_tb);
	
		t_a = 0;
		t_b = 0;
		t_carry_in = 0;
		#10
		$display("a=%d, b=%d, cin=%d, s=%d, cout=%d", t_a, t_b, t_carry_in, t_sum, t_carry_out);

		t_a = 0;
		t_b = 0;
		t_carry_in = 1;
		#10
		$display("a=%d, b=%d, cin=%d, s=%d, cout=%d", t_a, t_b, t_carry_in, t_sum, t_carry_out);

		t_a = 0;
		t_b = 1;
		t_carry_in = 0;
		#10
		$display("a=%d, b=%d, cin=%d, s=%d, cout=%d", t_a, t_b, t_carry_in, t_sum, t_carry_out);

		t_a = 0;
		t_b = 1;
		t_carry_in = 1;
		#10
		$display("a=%d, b=%d, cin=%d, s=%d, cout=%d", t_a, t_b, t_carry_in, t_sum, t_carry_out);

		t_a = 1;
		t_b = 0;
		t_carry_in = 0;
		#10
		$display("a=%d, b=%d, cin=%d, s=%d, cout=%d", t_a, t_b, t_carry_in, t_sum, t_carry_out);
	
		t_a = 1;
		t_b = 0;
		t_carry_in = 1;
		#10
		$display("a=%d, b=%d, cin=%d, s=%d, cout=%d", t_a, t_b, t_carry_in, t_sum, t_carry_out);
	
		t_a = 1;
		t_b = 1;
		t_carry_in = 0;
		#10
		$display("a=%d, b=%d, cin=%d, s=%d, cout=%d", t_a, t_b, t_carry_in, t_sum, t_carry_out);
	
		t_a = 1;
		t_b = 1;
		t_carry_in = 1;
		#10
		$display("a=%d, b=%d, cin=%d, s=%d, cout=%d", t_a, t_b, t_carry_in, t_sum, t_carry_out);
	
		$stop;
	end

endmodule

full_adder/simulation/haout.vcd
$date
	Tue Jul 27 02:46:29 2021
$end
$version
	ModelSim Version 2020.1
$end
$timescale
	1ns
$end

$scope module full_adder_tb $end
$var reg 1 ! t_a $end
$var reg 1 " t_b $end
$var reg 1 # t_carry_in $end
$var wire 1 $ t_sum $end
$var wire 1 % t_carry_out $end
$upscope $end
$enddefinitions $end
#0
$dumpvars
0!
0"
0#
0$
0%
$end
#10
1#
1$
#20
1"
0#
0$
1$
#30
1#
0$
1%
#40
1!
0"
0#
1$
0%
#50
1#
0$
1%
#60
1"
0#
1$
0$
#70
1#
1$
