above_and_beyond/hdl/alu.v
`timescale 1ns/1ns

module alu 
	(
		input [3:0] a,
		input [3:0] b,
		input [1:0] op,

		output reg [3:0] out,
		output reg overflow
	);

	always @* begin
		// Set overflow to default to 0
		// This removes any extra latches and keeps it combinational
		overflow <= 0;
		
		case(op)
			2'b00: {overflow, out} <= a + b; // Add
			2'b01: {overflow, out} <= a - b; // Subtract
			2'b10: out <= ~a; // Not
			2'b11: out <= a & b; // And
			default: out <= a + b;
		endcase
	end

endmodule

alu/testbench/alu_tb.v
`timescale 1ns/1ns

module alu_tb;
	// Inputs
	reg [3:0] t_a;
	reg [3:0] t_b;
	reg [1:0] t_op;

	// Outputs
	wire [3:0] t_out;
	wire t_overflow;

	// Instantiate the Unit Under Test (UUT)
	alu UUT (
		.a(t_a),
		.b(t_b),
		.op(t_op),
		.out(t_out),
		.overflow(t_overflow)
	);

	initial begin
		$dumpfile("haout.vcd");
		$dumpvars(1, alu_tb);
		
		t_a = 0;
		t_b = 0;
		t_op = 0;
		#10
		$display("a=%d, b=%d, op=%b, out=%f, overflow=%d", t_a, t_b, t_op, t_out, t_overflow);
		
		// 1 + 0 = 1
		t_a = 1;
		t_b = 0;
		t_op = 0;
		#10
		$display("a=%d, b=%d, op=%b, out=%f, overflow=%d", t_a, t_b, t_op, t_out, t_overflow);
		
		// 1 + 3 = 4
		t_a = 1;
		t_b = 3;
		t_op = 0;
		#10
		$display("a=%d, b=%d, op=%b, out=%f, overflow=%d", t_a, t_b, t_op, t_out, t_overflow);
		
		// 15 + 2 = 1 (+ overflow)
		t_a = 15;
		t_b = 2;
		t_op = 0;
		#10
		$display("a=%d, b=%d, op=%b, out=%f, overflow=%d", t_a, t_b, t_op, t_out, t_overflow);
		
		// 2 + 15 = 1 (+ overflow)
		t_a = 2;
		t_b = 15;
		t_op = 0;
		#10
		$display("a=%d, b=%d, op=%b, out=%f, overflow=%d", t_a, t_b, t_op, t_out, t_overflow);
		
		// 4 - 2 = 2
		t_a = 4;
		t_b = 2;
		t_op = 2'b01;
		#10
		$display("a=%d, b=%d, op=%b, out=%f, overflow=%d", t_a, t_b, t_op, t_out, t_overflow);
		
		// 2 - 4 = 14 (+ overflow)
		t_a = 2;
		t_b = 4;
		t_op = 2'b01;
		#10
		$display("a=%d, b=%d, op=%b, out=%f, overflow=%d", t_a, t_b, t_op, t_out, t_overflow);
		
		// 15 - 1 = 14
		t_a = 15;
		t_b = 1;
		t_op = 2'b01;
		#10
		$display("a=%d, b=%d, op=%b, out=%f, overflow=%d", t_a, t_b, t_op, t_out, t_overflow);
		
		// !2 = 13
		t_a = 2;
		t_b = 0;
		t_op = 2'b10;
		#10
		$display("a=%d, b=%d, op=%b, out=%f, overflow=%d", t_a, t_b, t_op, t_out, t_overflow);
		
		// !0 = 15 
		t_a = 0;
		t_b = 0;
		t_op = 2'b10;
		#10
		$display("a=%d, b=%d, op=%b, out=%f, overflow=%d", t_a, t_b, t_op, t_out, t_overflow);
		
		// !15 = 0
		t_a = 15;
		t_b = 0;
		t_op = 2'b10;
		#10
		$display("a=%d, b=%d, op=%b, out=%f, overflow=%d", t_a, t_b, t_op, t_out, t_overflow);
		
		// 10 AND 5 = 0
		t_a = 10;
		t_b = 5;
		t_op = 02'b11;
		#10
		$display("a=%d, b=%d, op=%b, out=%f, overflow=%d", t_a, t_b, t_op, t_out, t_overflow);
		
		// 11 AND 5 = 1
		t_a = 11;
		t_b = 5;
		t_op = 02'b11;
		#10
		$display("a=%d, b=%d, op=%b, out=%f, overflow=%d", t_a, t_b, t_op, t_out, t_overflow);
		
		$stop;
	end

endmodule

alu/simulation/haout.vcd
$date
	Tue Jul 27 23:42:40 2021
$end
$version
	ModelSim Version 2020.1
$end
$timescale
	1ns
$end

$scope module alu_tb $end
$var reg 4 ! t_a [3:0] $end
$var reg 4 " t_b [3:0] $end
$var reg 2 # t_op [1:0] $end
$var wire 1 $ t_out [3] $end
$var wire 1 % t_out [2] $end
$var wire 1 & t_out [1] $end
$var wire 1 ' t_out [0] $end
$var wire 1 ( t_overflow $end
$upscope $end
$enddefinitions $end
#0
$dumpvars
b0 !
b0 "
b0 #
0'
0&
0%
0$
0(
$end
#10
b1 !
1'
#20
b11 "
0'
1%
#30
b1111 !
b10 "
1'
0%
1(
#40
b10 !
b1111 "
#50
b100 !
b10 "
b1 #
0(
0'
1&
#60
b10 !
b100 "
1%
1$
1(
#70
b1111 !
b1 "
0(
#80
b10 !
b0 "
b10 #
1'
0&
#90
b0 !
1&
#100
b1111 !
0'
0&
0%
0$
#110
b1010 !
b101 "
b11 #
#120
b1011 !
1'
